pytkutils/__init__.py
pytkutils/compression.py
pytkutils/wrapper.py
pytkutils-0.1.3.dist-info/licenses/LICENSE
tests/__init__.py
tests/test_compression.py
tests/test_wrapper.py
pytkutils-0.1.3.dist-info/METADATA
pytkutils-0.1.3.dist-info/WHEEL
pytkutils-0.1.3.dist-info/top_level.txt
pytkutils-0.1.3.dist-info/RECORD
