Metadata-Version: 2.4
Name: pytkutils
Version: 0.1.3
Summary: A Python wrapper for the TK.MSTS.Tokens.dll library by Okrasa Ghia.
Author: Peter Grønbæk Andersen
Author-email: Peter Grønbæk Andersen <peter@grnbk.io>
License: GNU GPL v3
Project-URL: Homepage, https://github.com/pgroenbaek/pytkutils
Project-URL: Issues, https://github.com/pgroenbaek/pytkutils/issues
Project-URL: Source, https://github.com/pgroenbaek/pytkutils
Classifier: Programming Language :: Python :: 3
Classifier: License :: OSI Approved :: GNU General Public License v3 or later (GPLv3+)
Classifier: Operating System :: OS Independent
Requires-Python: >=3.7, <3.14
Requires-Dist: pythonnet<4.0.0,>=3.0.0
Dynamic: author
Dynamic: requires-python
